webex_assistant_sdk/__init__.py
webex_assistant_sdk/_version.py
webex_assistant_sdk/app.py
webex_assistant_sdk/cli.py
webex_assistant_sdk/crypto.py
webex_assistant_sdk/dialogue.py
webex_assistant_sdk/exceptions.py
webex_assistant_sdk/helpers.py
webex_assistant_sdk/server.py
webex_assistant_sdk/templates/mindmeld_template/cookiecutter.json
webex_assistant_sdk/templates/mindmeld_template/{{cookiecutter.skill_name}}/docker-compose.yml
webex_assistant_sdk/templates/mindmeld_template/{{cookiecutter.skill_name}}/requirements.txt
webex_assistant_sdk/templates/mindmeld_template/{{cookiecutter.skill_name}}/{{cookiecutter.skill_name}}/__init__.py
webex_assistant_sdk/templates/mindmeld_template/{{cookiecutter.skill_name}}/{{cookiecutter.skill_name}}/__main__.py
webex_assistant_sdk/templates/mindmeld_template/{{cookiecutter.skill_name}}/{{cookiecutter.skill_name}}/domains/greeting/exit/train.txt
webex_assistant_sdk/templates/mindmeld_template/{{cookiecutter.skill_name}}/{{cookiecutter.skill_name}}/domains/greeting/greet/train.txt
webex_assistant_sdk/templates/mindmeld_template/{{cookiecutter.skill_name}}/{{cookiecutter.skill_name}}/root.py
webex_assistant_sdk-1.0.0.dist-info/entry_points.txt
webex_assistant_sdk-1.0.0.dist-info/LICENSE
webex_assistant_sdk-1.0.0.dist-info/WHEEL
webex_assistant_sdk-1.0.0.dist-info/METADATA
webex_assistant_sdk-1.0.0.dist-info/RECORD
