Metadata-Version: 2.1
Name: webex-assistant-sdk
Version: 1.0.0
Summary: An SDK for developing applications for Webex Assistant.
Home-page: https://github.com/cisco/webex-assistant-sdk
License: MIT
Keywords: webex,webex-assistant,webex-teams
Author: Minh Vo Thanh
Author-email: minhtue@cisco.com
Requires-Python: >=3.7,<4.0
Classifier: Development Status :: 2 - Pre-Alpha
Classifier: Intended Audience :: Developers
Classifier: License :: OSI Approved :: MIT License
Classifier: Natural Language :: English
Classifier: Programming Language :: Python :: 3
Classifier: Programming Language :: Python :: 3.6
Classifier: Programming Language :: Python :: 3.7
Classifier: Programming Language :: Python :: 3.8
Classifier: Programming Language :: Python :: 3.9
Requires-Dist: cookiecutter (>=1.7.2,<2.0.0)
Requires-Dist: cryptography (>=2.8,<3.4)
Requires-Dist: mindmeld (>=4.3.5rc11,<5.0.0)
Requires-Dist: requests (>=2.22.0,<3.0.0)
Requires-Dist: spacy (>=2.3.0,<3.0.0)
Requires-Dist: typer (>=0.4.0,<0.5.0)
